{"callback": "http://your.domain/yourcallback", "forecast_to": 1767119400.0, "data": [{"timestamp": -284103000.0, "value": 59.212}, {"timestamp": -252567000.0, "value": 60.041}, {"timestamp": -221031000.0, "value": 60.871}, {"timestamp": -189495000.0, "value": 61.7}, {"timestamp": -157872600.0, "value": 62.526}, {"timestamp": -126336600.0, "value": 63.345}, {"timestamp": -94800600.0, "value": 64.155}, {"timestamp": -63264600.0, "value": 64.949}, {"timestamp": -31642200.0, "value": 65.719}, {"timestamp": -106200.0, "value": 66.458}, {"timestamp": 31429800.0, "value": 67.159}, {"timestamp": 62965800.0, "value": 67.814}, {"timestamp": 94588200.0, "value": 68.422}, {"timestamp": 126124200.0, "value": 68.984}, {"timestamp": 157660200.0, "value": 69.499}, {"timestamp": 189196200.0, "value": 69.968}, {"timestamp": 220818600.0, "value": 70.396}, {"timestamp": 252354600.0, "value": 70.789}, {"timestamp": 283890600.0, "value": 71.153}, {"timestamp": 315426600.0, "value": 71.494}, {"timestamp": 347049000.0, "value": 71.813}, {"timestamp": 378585000.0, "value": 72.114}, {"timestamp": 410121000.0, "value": 72.396}, {"timestamp": 441657000.0, "value": 72.66}, {"timestamp": 473279400.0, "value": 72.907}, {"timestamp": 504815400.0, "value": 73.14}, {"timestamp": 536351400.0, "value": 73.359}, {"timestamp": 567887400.0, "value": 73.564}, {"timestamp": 599509800.0, "value": 73.755}, {"timestamp": 631045800.0, "value": 73.934}, {"timestamp": 662581800.0, "value": 74.102}, {"timestamp": 694117800.0, "value": 74.26}, {"timestamp": 725740200.0, "value": 74.407}, {"timestamp": 757276200.0, "value": 74.544}, {"timestamp": 788812200.0, "value": 74.675}, {"timestamp": 820348200.0, "value": 74.799}, {"timestamp": 851970600.0, "value": 74.919}, {"timestamp": 883506600.0, "value": 75.036}, {"timestamp": 915042600.0, "value": 75.15}, {"timestamp": 946578600.0, "value": 75.261}, {"timestamp": 978201000.0, "value": 75.365}, {"timestamp": 1009737000.0, "value": 75.459}, {"timestamp": 1041273000.0, "value": 75.542}, {"timestamp": 1072809000.0, "value": 75.613}, {"timestamp": 1104431400.0, "value": 75.679}, {"timestamp": 1135967400.0, "value": 75.746}, {"timestamp": 1167503400.0, "value": 75.826}, {"timestamp": 1199039400.0, "value": 75.925}, {"timestamp": 1230661800.0, "value": 76.047}, {"timestamp": 1262197800.0, "value": 76.193}, {"timestamp": 1293733800.0, "value": 76.36}, {"timestamp": 1325269800.0, "value": 76.541}, {"timestamp": 1356892200.0, "value": 76.727}, {"timestamp": 1388428200.0, "value": 76.909}, {"timestamp": 1419964200.0, "value": 77.084}, {"timestamp": 1451500200.0, "value": 77.251}, {"timestamp": 1483122600.0, "value": 77.411}, {"timestamp": 1514658600.0, "value": 77.568}]}