{"data": [{"timestamp": -284103000.0, "value": 36505.0}, {"timestamp": -252567000.0, "value": 38292.0}, {"timestamp": -221031000.0, "value": 37831.0}, {"timestamp": -189495000.0, "value": 38443.0}, {"timestamp": -157872600.0, "value": 38877.0}, {"timestamp": -126336600.0, "value": 39066.0}, {"timestamp": -94800600.0, "value": 39680.0}, {"timestamp": -63264600.0, "value": 38594.0}, {"timestamp": -31642200.0, "value": 38056.0}, {"timestamp": -106200.0, "value": 37479.0}, {"timestamp": 31429800.0, "value": 36963.0}, {"timestamp": 62965800.0, "value": 35826.0}, {"timestamp": 94588200.0, "value": 36259.0}, {"timestamp": 126124200.0, "value": 35912.0}, {"timestamp": 157660200.0, "value": 35437.0}, {"timestamp": 189196200.0, "value": 34758.0}, {"timestamp": 220818600.0, "value": 34170.0}, {"timestamp": 252354600.0, "value": 32856.0}, {"timestamp": 283890600.0, "value": 31709.0}, {"timestamp": 315426600.0, "value": 30503.0}, {"timestamp": 347049000.0, "value": 29299.0}, {"timestamp": 378585000.0, "value": 27887.0}, {"timestamp": 410121000.0, "value": 27004.0}, {"timestamp": 441657000.0, "value": 26023.0}, {"timestamp": 473279400.0, "value": 25370.0}, {"timestamp": 504815400.0, "value": 25154.0}, {"timestamp": 536351400.0, "value": 24855.0}, {"timestamp": 567887400.0, "value": 26141.0}, {"timestamp": 599509800.0, "value": 27148.0}, {"timestamp": 631045800.0, "value": 28296.0}, {"timestamp": 662581800.0, "value": 29450.0}, {"timestamp": 694117800.0, "value": 31413.0}, {"timestamp": 725740200.0, "value": 31656.0}, {"timestamp": 757276200.0, "value": 32643.0}, {"timestamp": 788812200.0, "value": 33392.0}, {"timestamp": 820348200.0, "value": 33826.0}, {"timestamp": 851970600.0, "value": 34422.0}, {"timestamp": 883506600.0, "value": 33607.0}, {"timestamp": 915042600.0, "value": 33129.0}, {"timestamp": 946578600.0, "value": 32609.0}, {"timestamp": 978201000.0, "value": 32176.0}, {"timestamp": 1009737000.0, "value": 30876.0}, {"timestamp": 1041273000.0, "value": 31751.0}, {"timestamp": 1072809000.0, "value": 31657.0}, {"timestamp": 1104431400.0, "value": 31641.0}, {"timestamp": 1135967400.0, "value": 31688.0}, {"timestamp": 1167503400.0, "value": 31740.0}, {"timestamp": 1199039400.0, "value": 31992.0}, {"timestamp": 1230661800.0, "value": 32160.0}, {"timestamp": 1262197800.0, "value": 32124.0}, {"timestamp": 1293733800.0, "value": 31777.0}, {"timestamp": 1325269800.0, "value": 31981.0}, {"timestamp": 1356892200.0, "value": 29945.0}, {"timestamp": 1388428200.0, "value": 28809.0}, {"timestamp": 1419964200.0, "value": 27910.0}, {"timestamp": 1451500200.0, "value": 27472.0}, {"timestamp": 1483122600.0, "value": 25941.0}, {"timestamp": 1514658600.0, "value": 28333.0}], "callback": "http://your.domain/yourcallback", "forecast_to": 1767119400.0}