{"data": [{"timestamp": -284103000.0, "value": 36189.0}, {"timestamp": -252567000.0, "value": 35637.0}, {"timestamp": -221031000.0, "value": 35088.0}, {"timestamp": -189495000.0, "value": 34534.0}, {"timestamp": -157872600.0, "value": 34075.0}, {"timestamp": -126336600.0, "value": 33533.0}, {"timestamp": -94800600.0, "value": 33297.0}, {"timestamp": -63264600.0, "value": 33030.0}, {"timestamp": -31642200.0, "value": 31471.0}, {"timestamp": -106200.0, "value": 30917.0}, {"timestamp": 31429800.0, "value": 30561.0}, {"timestamp": 62965800.0, "value": 30036.0}, {"timestamp": 94588200.0, "value": 29673.0}, {"timestamp": 126124200.0, "value": 30838.0}, {"timestamp": 157660200.0, "value": 31119.0}, {"timestamp": 189196200.0, "value": 31381.0}, {"timestamp": 220818600.0, "value": 32367.0}, {"timestamp": 252354600.0, "value": 33266.0}, {"timestamp": 283890600.0, "value": 31733.0}, {"timestamp": 315426600.0, "value": 31803.0}, {"timestamp": 347049000.0, "value": 31848.0}, {"timestamp": 378585000.0, "value": 31230.0}, {"timestamp": 410121000.0, "value": 30627.0}, {"timestamp": 441657000.0, "value": 31729.0}, {"timestamp": 473279400.0, "value": 31558.0}, {"timestamp": 504815400.0, "value": 31307.0}, {"timestamp": 536351400.0, "value": 31413.0}, {"timestamp": 567887400.0, "value": 31380.0}, {"timestamp": 599509800.0, "value": 30222.0}, {"timestamp": 631045800.0, "value": 29572.0}, {"timestamp": 662581800.0, "value": 28702.0}, {"timestamp": 694117800.0, "value": 27598.0}, {"timestamp": 725740200.0, "value": 26398.0}, {"timestamp": 757276200.0, "value": 25437.0}, {"timestamp": 788812200.0, "value": 24385.0}, {"timestamp": 820348200.0, "value": 23615.0}, {"timestamp": 851970600.0, "value": 22680.0}, {"timestamp": 883506600.0, "value": 21964.0}, {"timestamp": 915042600.0, "value": 23190.0}, {"timestamp": 946578600.0, "value": 23237.0}, {"timestamp": 978201000.0, "value": 23146.0}, {"timestamp": 1009737000.0, "value": 24027.0}, {"timestamp": 1041273000.0, "value": 24731.0}, {"timestamp": 1072809000.0, "value": 21430.0}, {"timestamp": 1104431400.0, "value": 20880.0}, {"timestamp": 1135967400.0, "value": 20502.0}, {"timestamp": 1167503400.0, "value": 18928.0}, {"timestamp": 1199039400.0, "value": 17619.0}, {"timestamp": 1230661800.0, "value": 20533.0}, {"timestamp": 1262197800.0, "value": 20667.0}, {"timestamp": 1293733800.0, "value": 20760.0}, {"timestamp": 1325269800.0, "value": 21996.0}, {"timestamp": 1356892200.0, "value": 23065.0}, {"timestamp": 1388428200.0, "value": 20725.0}, {"timestamp": 1419964200.0, "value": 20568.0}, {"timestamp": 1451500200.0, "value": 20300.0}, {"timestamp": 1483122600.0, "value": 19254.0}, {"timestamp": 1514658600.0, "value": 18212.0}], "callback": "http://your.domain/yourcallback", "forecast_to": 1767119400.0}