{"callback": "http://your.domain/yourcallback", "data": [{"value": 28419.0, "timestamp": -284103000.0}, {"value": 30254.0, "timestamp": -252567000.0}, {"value": 32004.0, "timestamp": -221031000.0}, {"value": 33506.0, "timestamp": -189495000.0}, {"value": 34547.0, "timestamp": -157872600.0}, {"value": 34901.0, "timestamp": -126336600.0}, {"value": 34943.0, "timestamp": -94800600.0}, {"value": 34582.0, "timestamp": -63264600.0}, {"value": 33914.0, "timestamp": -31642200.0}, {"value": 33066.0, "timestamp": -106200.0}, {"value": 32216.0, "timestamp": 31429800.0}, {"value": 30766.0, "timestamp": 62965800.0}, {"value": 29206.0, "timestamp": 94588200.0}, {"value": 27900.0, "timestamp": 126124200.0}, {"value": 27290.0, "timestamp": 157660200.0}, {"value": 27856.0, "timestamp": 189196200.0}, {"value": 28389.0, "timestamp": 220818600.0}, {"value": 29300.0, "timestamp": 252354600.0}, {"value": 30319.0, "timestamp": 283890600.0}, {"value": 31060.0, "timestamp": 315426600.0}, {"value": 31073.0, "timestamp": 347049000.0}, {"value": 31476.0, "timestamp": 378585000.0}, {"value": 31786.0, "timestamp": 410121000.0}, {"value": 32124.0, "timestamp": 441657000.0}, {"value": 32664.0, "timestamp": 473279400.0}, {"value": 33582.0, "timestamp": 504815400.0}, {"value": 34920.0, "timestamp": 536351400.0}, {"value": 36354.0, "timestamp": 567887400.0}, {"value": 37572.0, "timestamp": 599509800.0}, {"value": 38183.0, "timestamp": 631045800.0}, {"value": 37823.0, "timestamp": 662581800.0}, {"value": 37322.0, "timestamp": 694117800.0}, {"value": 36380.0, "timestamp": 725740200.0}, {"value": 35080.0, "timestamp": 757276200.0}, {"value": 33541.0, "timestamp": 788812200.0}, {"value": 31818.0, "timestamp": 820348200.0}, {"value": 29781.0, "timestamp": 851970600.0}, {"value": 27608.0, "timestamp": 883506600.0}, {"value": 25418.0, "timestamp": 915042600.0}, {"value": 23368.0, "timestamp": 946578600.0}, {"value": 21698.0, "timestamp": 978201000.0}, {"value": 19819.0, "timestamp": 1009737000.0}, {"value": 18063.0, "timestamp": 1041273000.0}, {"value": 16611.0, "timestamp": 1072809000.0}, {"value": 15682.0, "timestamp": 1104431400.0}, {"value": 15522.0, "timestamp": 1135967400.0}, {"value": 15731.0, "timestamp": 1167503400.0}, {"value": 16298.0, "timestamp": 1199039400.0}, {"value": 16990.0, "timestamp": 1230661800.0}, {"value": 17493.0, "timestamp": 1262197800.0}, {"value": 17413.0, "timestamp": 1293733800.0}, {"value": 17991.0, "timestamp": 1325269800.0}, {"value": 18620.0, "timestamp": 1356892200.0}, {"value": 19204.0, "timestamp": 1388428200.0}, {"value": 19625.0, "timestamp": 1419964200.0}, {"value": 19759.0, "timestamp": 1451500200.0}, {"value": 19727.0, "timestamp": 1483122600.0}, {"value": 19511.0, "timestamp": 1514658600.0}], "forecast_to": 1767119400.0}