{"callback": "http://your.domain/yourcallback", "data": [{"timestamp": -284103000.0, "value": 25.078}, {"timestamp": -252567000.0, "value": 24.858}, {"timestamp": -221031000.0, "value": 24.511}, {"timestamp": -189495000.0, "value": 24.053}, {"timestamp": -157872600.0, "value": 23.507}, {"timestamp": -126336600.0, "value": 22.898}, {"timestamp": -94800600.0, "value": 22.253}, {"timestamp": -63264600.0, "value": 21.6}, {"timestamp": -31642200.0, "value": 20.969}, {"timestamp": -106200.0, "value": 20.386}, {"timestamp": 31429800.0, "value": 19.874}, {"timestamp": 62965800.0, "value": 19.448}, {"timestamp": 94588200.0, "value": 19.101}, {"timestamp": 126124200.0, "value": 18.826}, {"timestamp": 157660200.0, "value": 18.624}, {"timestamp": 189196200.0, "value": 18.493}, {"timestamp": 220818600.0, "value": 18.432}, {"timestamp": 252354600.0, "value": 18.427}, {"timestamp": 283890600.0, "value": 18.462}, {"timestamp": 315426600.0, "value": 18.519}, {"timestamp": 347049000.0, "value": 18.589}, {"timestamp": 378585000.0, "value": 18.664}, {"timestamp": 410121000.0, "value": 18.734}, {"timestamp": 441657000.0, "value": 18.786}, {"timestamp": 473279400.0, "value": 18.798}, {"timestamp": 504815400.0, "value": 18.747}, {"timestamp": 536351400.0, "value": 18.609}, {"timestamp": 567887400.0, "value": 18.377}, {"timestamp": 599509800.0, "value": 18.05}, {"timestamp": 631045800.0, "value": 17.634}, {"timestamp": 662581800.0, "value": 17.131}, {"timestamp": 694117800.0, "value": 16.553}, {"timestamp": 725740200.0, "value": 15.925}, {"timestamp": 757276200.0, "value": 15.279}, {"timestamp": 788812200.0, "value": 14.64}, {"timestamp": 820348200.0, "value": 14.032}, {"timestamp": 851970600.0, "value": 13.472}, {"timestamp": 883506600.0, "value": 12.97}, {"timestamp": 915042600.0, "value": 12.539}, {"timestamp": 946578600.0, "value": 12.196}, {"timestamp": 978201000.0, "value": 11.967}, {"timestamp": 1009737000.0, "value": 11.873}, {"timestamp": 1041273000.0, "value": 11.91}, {"timestamp": 1072809000.0, "value": 12.064}, {"timestamp": 1104431400.0, "value": 12.314}, {"timestamp": 1135967400.0, "value": 12.638}, {"timestamp": 1167503400.0, "value": 13.007}, {"timestamp": 1199039400.0, "value": 13.384}, {"timestamp": 1230661800.0, "value": 13.734}, {"timestamp": 1262197800.0, "value": 14.026}, {"timestamp": 1293733800.0, "value": 14.231}, {"timestamp": 1325269800.0, "value": 14.327}, {"timestamp": 1356892200.0, "value": 14.32}, {"timestamp": 1388428200.0, "value": 14.223}, {"timestamp": 1419964200.0, "value": 14.043}, {"timestamp": 1451500200.0, "value": 13.795}, {"timestamp": 1483122600.0, "value": 13.499}, {"timestamp": 1514658600.0, "value": 13.18}], "forecast_to": 1767119400.0}