{"data": [{"value": 24563.0, "timestamp": -284103000.0}, {"value": 26029.0, "timestamp": -252567000.0}, {"value": 27282.0, "timestamp": -221031000.0}, {"value": 28385.0, "timestamp": -189495000.0}, {"value": 29448.0, "timestamp": -157872600.0}, {"value": 30607.0, "timestamp": -126336600.0}, {"value": 31806.0, "timestamp": -94800600.0}, {"value": 32962.0, "timestamp": -63264600.0}, {"value": 33996.0, "timestamp": -31642200.0}, {"value": 34789.0, "timestamp": -106200.0}, {"value": 35217.0, "timestamp": 31429800.0}, {"value": 35512.0, "timestamp": 62965800.0}, {"value": 35654.0, "timestamp": 94588200.0}, {"value": 35782.0, "timestamp": 126124200.0}, {"value": 36087.0, "timestamp": 157660200.0}, {"value": 36782.0, "timestamp": 189196200.0}, {"value": 37439.0, "timestamp": 220818600.0}, {"value": 38173.0, "timestamp": 252354600.0}, {"value": 38963.0, "timestamp": 283890600.0}, {"value": 39772.0, "timestamp": 315426600.0}, {"value": 40556.0, "timestamp": 347049000.0}, {"value": 41481.0, "timestamp": 378585000.0}, {"value": 42449.0, "timestamp": 410121000.0}, {"value": 43415.0, "timestamp": 441657000.0}, {"value": 44321.0, "timestamp": 473279400.0}, {"value": 45107.0, "timestamp": 504815400.0}, {"value": 46111.0, "timestamp": 536351400.0}, {"value": 47063.0, "timestamp": 567887400.0}, {"value": 48050.0, "timestamp": 599509800.0}, {"value": 49199.0, "timestamp": 631045800.0}, {"value": 50627.0, "timestamp": 662581800.0}, {"value": 52609.0, "timestamp": 694117800.0}, {"value": 54906.0, "timestamp": 725740200.0}, {"value": 57161.0, "timestamp": 757276200.0}, {"value": 58906.0, "timestamp": 788812200.0}, {"value": 59632.0, "timestamp": 820348200.0}, {"value": 59943.0, "timestamp": 851970600.0}, {"value": 59648.0, "timestamp": 883506600.0}, {"value": 58788.0, "timestamp": 915042600.0}, {"value": 57436.0, "timestamp": 946578600.0}, {"value": 55724.0, "timestamp": 978201000.0}, {"value": 53451.0, "timestamp": 1009737000.0}, {"value": 50562.0, "timestamp": 1041273000.0}, {"value": 47638.0, "timestamp": 1072809000.0}, {"value": 45422.0, "timestamp": 1104431400.0}, {"value": 44737.0, "timestamp": 1135967400.0}, {"value": 45091.0, "timestamp": 1167503400.0}, {"value": 46475.0, "timestamp": 1199039400.0}, {"value": 48399.0, "timestamp": 1230661800.0}, {"value": 50121.0, "timestamp": 1262197800.0}, {"value": 50748.0, "timestamp": 1293733800.0}, {"value": 51364.0, "timestamp": 1325269800.0}, {"value": 51754.0, "timestamp": 1356892200.0}, {"value": 52242.0, "timestamp": 1388428200.0}, {"value": 53325.0, "timestamp": 1419964200.0}, {"value": 55561.0, "timestamp": 1451500200.0}, {"value": 58736.0, "timestamp": 1483122600.0}, {"value": 62616.0, "timestamp": 1514658600.0}], "callback": "http://your.domain/yourcallback", "forecast_to": 1767119400.0}