{"callback": "http://your.domain/yourcallback", "data": [{"timestamp": -284103000.0, "value": 37.601}, {"timestamp": -252567000.0, "value": 37.994}, {"timestamp": -221031000.0, "value": 38.025}, {"timestamp": -189495000.0, "value": 37.659}, {"timestamp": -157872600.0, "value": 36.928}, {"timestamp": -126336600.0, "value": 35.932}, {"timestamp": -94800600.0, "value": 34.819}, {"timestamp": -63264600.0, "value": 33.754}, {"timestamp": -31642200.0, "value": 32.863}, {"timestamp": -106200.0, "value": 32.201}, {"timestamp": 31429800.0, "value": 31.779}, {"timestamp": 62965800.0, "value": 31.555}, {"timestamp": 94588200.0, "value": 31.419}, {"timestamp": 126124200.0, "value": 31.279}, {"timestamp": 157660200.0, "value": 31.098}, {"timestamp": 189196200.0, "value": 30.837}, {"timestamp": 220818600.0, "value": 30.472}, {"timestamp": 252354600.0, "value": 30.023}, {"timestamp": 283890600.0, "value": 29.515}, {"timestamp": 315426600.0, "value": 28.968}, {"timestamp": 347049000.0, "value": 28.432}, {"timestamp": 378585000.0, "value": 27.965}, {"timestamp": 410121000.0, "value": 27.603}, {"timestamp": 441657000.0, "value": 27.358}, {"timestamp": 473279400.0, "value": 27.22}, {"timestamp": 504815400.0, "value": 27.14}, {"timestamp": 536351400.0, "value": 27.044}, {"timestamp": 567887400.0, "value": 26.866}, {"timestamp": 599509800.0, "value": 26.565}, {"timestamp": 631045800.0, "value": 26.138}, {"timestamp": 662581800.0, "value": 25.615}, {"timestamp": 694117800.0, "value": 25.055}, {"timestamp": 725740200.0, "value": 24.526}, {"timestamp": 757276200.0, "value": 24.076}, {"timestamp": 788812200.0, "value": 23.718}, {"timestamp": 820348200.0, "value": 23.439}, {"timestamp": 851970600.0, "value": 23.206}, {"timestamp": 883506600.0, "value": 22.967}, {"timestamp": 915042600.0, "value": 22.684}, {"timestamp": 946578600.0, "value": 22.343}, {"timestamp": 978201000.0, "value": 21.937}, {"timestamp": 1009737000.0, "value": 21.469}, {"timestamp": 1041273000.0, "value": 20.963}, {"timestamp": 1072809000.0, "value": 20.446}, {"timestamp": 1104431400.0, "value": 19.932}, {"timestamp": 1135967400.0, "value": 19.441}, {"timestamp": 1167503400.0, "value": 18.987}, {"timestamp": 1199039400.0, "value": 18.58}, {"timestamp": 1230661800.0, "value": 18.223}, {"timestamp": 1262197800.0, "value": 17.919}, {"timestamp": 1293733800.0, "value": 17.669}, {"timestamp": 1325269800.0, "value": 17.467}, {"timestamp": 1356892200.0, "value": 17.299}, {"timestamp": 1388428200.0, "value": 17.153}, {"timestamp": 1419964200.0, "value": 17.021}, {"timestamp": 1451500200.0, "value": 16.897}, {"timestamp": 1483122600.0, "value": 16.78}, {"timestamp": 1514658600.0, "value": 16.667}], "forecast_to": 1767119400.0}