{"callback": "http://your.domain/yourcallback", "data": [{"timestamp": -284103000.0, "value": 141.4524}, {"timestamp": -252567000.0, "value": 143.1922}, {"timestamp": -221031000.0, "value": 144.932}, {"timestamp": -189495000.0, "value": 145.6196}, {"timestamp": -157872600.0, "value": 146.3072}, {"timestamp": -126336600.0, "value": 146.9948}, {"timestamp": -94800600.0, "value": 147.6824}, {"timestamp": -63264600.0, "value": 148.37}, {"timestamp": -31642200.0, "value": 142.8118}, {"timestamp": -106200.0, "value": 137.2536}, {"timestamp": 31429800.0, "value": 131.6954}, {"timestamp": 62965800.0, "value": 126.1372}, {"timestamp": 94588200.0, "value": 120.579}, {"timestamp": 126124200.0, "value": 116.3492}, {"timestamp": 157660200.0, "value": 112.1194}, {"timestamp": 189196200.0, "value": 107.8896}, {"timestamp": 220818600.0, "value": 103.6598}, {"timestamp": 252354600.0, "value": 99.43}, {"timestamp": 283890600.0, "value": 96.2798}, {"timestamp": 315426600.0, "value": 93.1296}, {"timestamp": 347049000.0, "value": 89.9794}, {"timestamp": 378585000.0, "value": 86.8292}, {"timestamp": 410121000.0, "value": 83.679}, {"timestamp": 441657000.0, "value": 81.955}, {"timestamp": 473279400.0, "value": 80.231}, {"timestamp": 504815400.0, "value": 78.507}, {"timestamp": 536351400.0, "value": 76.783}, {"timestamp": 567887400.0, "value": 75.059}, {"timestamp": 599509800.0, "value": 73.5382}, {"timestamp": 631045800.0, "value": 72.0174}, {"timestamp": 662581800.0, "value": 70.4966}, {"timestamp": 694117800.0, "value": 68.9758}, {"timestamp": 725740200.0, "value": 67.455}, {"timestamp": 757276200.0, "value": 66.9284}, {"timestamp": 788812200.0, "value": 66.4018}, {"timestamp": 820348200.0, "value": 65.8752}, {"timestamp": 851970600.0, "value": 65.3486}, {"timestamp": 883506600.0, "value": 64.822}, {"timestamp": 915042600.0, "value": 65.0574}, {"timestamp": 946578600.0, "value": 65.2928}, {"timestamp": 978201000.0, "value": 65.5282}, {"timestamp": 1009737000.0, "value": 65.7636}, {"timestamp": 1041273000.0, "value": 65.999}, {"timestamp": 1072809000.0, "value": 68.4894}, {"timestamp": 1104431400.0, "value": 70.9798}, {"timestamp": 1135967400.0, "value": 73.4702}, {"timestamp": 1167503400.0, "value": 75.9606}, {"timestamp": 1199039400.0, "value": 78.451}, {"timestamp": 1230661800.0, "value": 78.451}, {"timestamp": 1262197800.0, "value": 78.451}, {"timestamp": 1293733800.0, "value": 78.451}, {"timestamp": 1325269800.0, "value": 78.451}, {"timestamp": 1356892200.0, "value": 78.451}, {"timestamp": 1388428200.0, "value": 78.788}, {"timestamp": 1419964200.0, "value": 79.125}, {"timestamp": 1451500200.0, "value": 79.462}, {"timestamp": 1483122600.0, "value": 79.799}, {"timestamp": 1514658600.0, "value": 80.136}], "forecast_to": 1767119400.0}