{
  "callback": "http://your.domain/yourcallback",
  "forecast_to": 1767119400.0,
  "data": [
    { "value": 767.0, "timestamp": 1514658600.0 },
    { "value": 800.0, "timestamp": 1483122600.0 },
    { "value": 838.0, "timestamp": 1451500200.0 },
    { "value": 878.0, "timestamp": 1419964200.0 },
    { "value": 922.0, "timestamp": 1388428200.0 },
    { "value": 969.0, "timestamp": 1356892200.0 },
    { "value": 1020.0, "timestamp": 1325269800.0 },
    { "value": 1074.0, "timestamp": 1293733800.0 },
    { "value": 1130.0, "timestamp": 1262197800.0 },
    { "value": 1187.0, "timestamp": 1230661800.0 },
    { "value": 1241.0, "timestamp": 1199039400.0 },
    { "value": 1294.0, "timestamp": 1167503400.0 },
    { "value": 1347.0, "timestamp": 1135967400.0 },
    { "value": 1401.0, "timestamp": 1104431400.0 },
    { "value": 1454.0, "timestamp": 1072809000.0 },
    { "value": 1508.0, "timestamp": 1041273000.0 },
    { "value": 1562.0, "timestamp": 1009737000.0 },
    { "value": 1615.0, "timestamp": 978201000.0 },
    { "value": 1666.0, "timestamp": 946578600.0 },
    { "value": 1716.0, "timestamp": 915042600.0 },
    { "value": 1763.0, "timestamp": 883506600.0 },
    { "value": 1809.0, "timestamp": 851970600.0 },
    { "value": 1855.0, "timestamp": 820348200.0 },
    { "value": 1900.0, "timestamp": 788812200.0 },
    { "value": 1946.0, "timestamp": 757276200.0 },
    { "value": 1993.0, "timestamp": 725740200.0 },
    { "value": 2040.0, "timestamp": 694117800.0 },
    { "value": 2088.0, "timestamp": 662581800.0 }
  ]
}