{"data": [{"timestamp": -284103000.0, "value": 30008.0}, {"timestamp": -252567000.0, "value": 30913.0}, {"timestamp": -221031000.0, "value": 31358.0}, {"timestamp": -189495000.0, "value": 31532.0}, {"timestamp": -157872600.0, "value": 31728.0}, {"timestamp": -126336600.0, "value": 32298.0}, {"timestamp": -94800600.0, "value": 32797.0}, {"timestamp": -63264600.0, "value": 33277.0}, {"timestamp": -31642200.0, "value": 33714.0}, {"timestamp": -106200.0, "value": 34048.0}, {"timestamp": 31429800.0, "value": 34165.0}, {"timestamp": 62965800.0, "value": 34480.0}, {"timestamp": 94588200.0, "value": 34786.0}, {"timestamp": 126124200.0, "value": 35027.0}, {"timestamp": 157660200.0, "value": 35154.0}, {"timestamp": 189196200.0, "value": 35184.0}, {"timestamp": 220818600.0, "value": 35403.0}, {"timestamp": 252354600.0, "value": 35482.0}, {"timestamp": 283890600.0, "value": 35476.0}, {"timestamp": 315426600.0, "value": 35459.0}, {"timestamp": 347049000.0, "value": 35459.0}, {"timestamp": 378585000.0, "value": 35201.0}, {"timestamp": 410121000.0, "value": 35086.0}, {"timestamp": 441657000.0, "value": 35025.0}, {"timestamp": 473279400.0, "value": 34910.0}, {"timestamp": 504815400.0, "value": 34664.0}, {"timestamp": 536351400.0, "value": 34308.0}, {"timestamp": 567887400.0, "value": 33813.0}, {"timestamp": 599509800.0, "value": 33245.0}, {"timestamp": 631045800.0, "value": 32680.0}, {"timestamp": 662581800.0, "value": 32141.0}, {"timestamp": 694117800.0, "value": 31927.0}, {"timestamp": 725740200.0, "value": 31924.0}, {"timestamp": 757276200.0, "value": 32036.0}, {"timestamp": 788812200.0, "value": 32170.0}, {"timestamp": 820348200.0, "value": 32319.0}, {"timestamp": 851970600.0, "value": 32341.0}, {"timestamp": 883506600.0, "value": 32202.0}, {"timestamp": 915042600.0, "value": 32014.0}, {"timestamp": 946578600.0, "value": 31911.0}, {"timestamp": 978201000.0, "value": 31894.0}, {"timestamp": 1009737000.0, "value": 32954.0}, {"timestamp": 1041273000.0, "value": 34097.0}, {"timestamp": 1072809000.0, "value": 35026.0}, {"timestamp": 1104431400.0, "value": 35424.0}, {"timestamp": 1135967400.0, "value": 35165.0}, {"timestamp": 1167503400.0, "value": 34753.0}, {"timestamp": 1199039400.0, "value": 33966.0}, {"timestamp": 1230661800.0, "value": 33054.0}, {"timestamp": 1262197800.0, "value": 32284.0}, {"timestamp": 1293733800.0, "value": 31719.0}, {"timestamp": 1325269800.0, "value": 33264.0}, {"timestamp": 1356892200.0, "value": 35250.0}, {"timestamp": 1388428200.0, "value": 37546.0}, {"timestamp": 1419964200.0, "value": 40029.0}, {"timestamp": 1451500200.0, "value": 42733.0}, {"timestamp": 1483122600.0, "value": 43909.0}, {"timestamp": 1514658600.0, "value": 45140.0}], "forecast_to": 1767119400.0, "callback": "http://your.domain/yourcallback"}