{"data": [{"value": 38312.0, "timestamp": -284103000.0}, {"value": 39398.0, "timestamp": -252567000.0}, {"value": 40155.0, "timestamp": -221031000.0}, {"value": 40991.0, "timestamp": -189495000.0}, {"value": 44013.0, "timestamp": -157872600.0}, {"value": 45199.0, "timestamp": -126336600.0}, {"value": 46973.0, "timestamp": -94800600.0}, {"value": 48640.0, "timestamp": -63264600.0}, {"value": 50038.0, "timestamp": -31642200.0}, {"value": 50130.0, "timestamp": -106200.0}, {"value": 51130.0, "timestamp": 31429800.0}, {"value": 51645.0, "timestamp": 62965800.0}, {"value": 52078.0, "timestamp": 94588200.0}, {"value": 52636.0, "timestamp": 126124200.0}, {"value": 54325.0, "timestamp": 157660200.0}, {"value": 55235.0, "timestamp": 189196200.0}, {"value": 56774.0, "timestamp": 220818600.0}, {"value": 58381.0, "timestamp": 252354600.0}, {"value": 59921.0, "timestamp": 283890600.0}, {"value": 60264.0, "timestamp": 315426600.0}, {"value": 62018.0, "timestamp": 347049000.0}, {"value": 63736.0, "timestamp": 378585000.0}, {"value": 65587.0, "timestamp": 410121000.0}, {"value": 67771.0, "timestamp": 441657000.0}, {"value": 71129.0, "timestamp": 473279400.0}, {"value": 74206.0, "timestamp": 504815400.0}, {"value": 78344.0, "timestamp": 536351400.0}, {"value": 82593.0, "timestamp": 567887400.0}, {"value": 86532.0, "timestamp": 599509800.0}, {"value": 88835.0, "timestamp": 631045800.0}, {"value": 91428.0, "timestamp": 662581800.0}, {"value": 94410.0, "timestamp": 694117800.0}, {"value": 96793.0, "timestamp": 725740200.0}, {"value": 98161.0, "timestamp": 757276200.0}, {"value": 96170.0, "timestamp": 788812200.0}, {"value": 95836.0, "timestamp": 820348200.0}, {"value": 93938.0, "timestamp": 851970600.0}, {"value": 91544.0, "timestamp": 883506600.0}, {"value": 89424.0, "timestamp": 915042600.0}, {"value": 90805.0, "timestamp": 946578600.0}, {"value": 89950.0, "timestamp": 978201000.0}, {"value": 90214.0, "timestamp": 1009737000.0}, {"value": 90789.0, "timestamp": 1041273000.0}, {"value": 91207.0, "timestamp": 1072809000.0}, {"value": 88695.0, "timestamp": 1104431400.0}, {"value": 89059.0, "timestamp": 1135967400.0}, {"value": 88083.0, "timestamp": 1167503400.0}, {"value": 87357.0, "timestamp": 1199039400.0}, {"value": 87687.0, "timestamp": 1230661800.0}, {"value": 92931.0, "timestamp": 1262197800.0}, {"value": 95613.0, "timestamp": 1293733800.0}, {"value": 101504.0, "timestamp": 1325269800.0}, {"value": 107872.0, "timestamp": 1356892200.0}, {"value": 113603.0, "timestamp": 1388428200.0}, {"value": 113423.0, "timestamp": 1419964200.0}, {"value": 117280.0, "timestamp": 1451500200.0}, {"value": 119978.0, "timestamp": 1483122600.0}, {"value": 122125.0, "timestamp": 1514658600.0}], "callback": "http://your.domain/yourcallback", "forecast_to": 1767119400.0}