{"callback": "http://your.domain/yourcallback", "data": [{"timestamp": -284103000.0, "value": 56570.0}, {"timestamp": -252567000.0, "value": 58231.0}, {"timestamp": -221031000.0, "value": 59465.0}, {"timestamp": -189495000.0, "value": 60398.0}, {"timestamp": -157872600.0, "value": 61268.0}, {"timestamp": -126336600.0, "value": 62357.0}, {"timestamp": -94800600.0, "value": 64173.0}, {"timestamp": -63264600.0, "value": 66060.0}, {"timestamp": -31642200.0, "value": 67819.0}, {"timestamp": -106200.0, "value": 69186.0}, {"timestamp": 31429800.0, "value": 69889.0}, {"timestamp": 62965800.0, "value": 71010.0}, {"timestamp": 94588200.0, "value": 71874.0}, {"timestamp": 126124200.0, "value": 72508.0}, {"timestamp": 157660200.0, "value": 72976.0}, {"timestamp": 189196200.0, "value": 73364.0}, {"timestamp": 220818600.0, "value": 74282.0}, {"timestamp": 252354600.0, "value": 75141.0}, {"timestamp": 283890600.0, "value": 76077.0}, {"timestamp": 315426600.0, "value": 77271.0}, {"timestamp": 347049000.0, "value": 78936.0}, {"timestamp": 378585000.0, "value": 81782.0}, {"timestamp": 410121000.0, "value": 85179.0}, {"timestamp": 441657000.0, "value": 88898.0}, {"timestamp": 473279400.0, "value": 92652.0}, {"timestamp": 504815400.0, "value": 96078.0}, {"timestamp": 536351400.0, "value": 100408.0}, {"timestamp": 567887400.0, "value": 105016.0}, {"timestamp": 599509800.0, "value": 109390.0}, {"timestamp": 631045800.0, "value": 112858.0}, {"timestamp": 662581800.0, "value": 114703.0}, {"timestamp": 694117800.0, "value": 115964.0}, {"timestamp": 725740200.0, "value": 116085.0}, {"timestamp": 757276200.0, "value": 115541.0}, {"timestamp": 788812200.0, "value": 115029.0}, {"timestamp": 820348200.0, "value": 115363.0}, {"timestamp": 851970600.0, "value": 116038.0}, {"timestamp": 883506600.0, "value": 116872.0}, {"timestamp": 915042600.0, "value": 117744.0}, {"timestamp": 946578600.0, "value": 118462.0}, {"timestamp": 978201000.0, "value": 118800.0}, {"timestamp": 1009737000.0, "value": 119653.0}, {"timestamp": 1041273000.0, "value": 120606.0}, {"timestamp": 1072809000.0, "value": 121496.0}, {"timestamp": 1104431400.0, "value": 122121.0}, {"timestamp": 1135967400.0, "value": 122252.0}, {"timestamp": 1167503400.0, "value": 122495.0}, {"timestamp": 1199039400.0, "value": 122529.0}, {"timestamp": 1230661800.0, "value": 122447.0}, {"timestamp": 1262197800.0, "value": 122403.0}, {"timestamp": 1293733800.0, "value": 122574.0}, {"timestamp": 1325269800.0, "value": 123202.0}, {"timestamp": 1356892200.0, "value": 124007.0}, {"timestamp": 1388428200.0, "value": 124779.0}, {"timestamp": 1419964200.0, "value": 125235.0}, {"timestamp": 1451500200.0, "value": 125062.0}, {"timestamp": 1483122600.0, "value": 124983.0}, {"timestamp": 1514658600.0, "value": 124634.0}], "forecast_to": 1767119400.0}