{"callback": "http://your.domain/yourcallback", "data": [{"timestamp": -284103000.0, "value": 86200.0}, {"timestamp": -252567000.0, "value": 78300.0}, {"timestamp": -221031000.0, "value": 70407.0}, {"timestamp": -189495000.0, "value": 71632.0}, {"timestamp": -157872600.0, "value": 67427.0}, {"timestamp": -126336600.0, "value": 64711.0}, {"timestamp": -94800600.0, "value": 62135.0}, {"timestamp": -63264600.0, "value": 60794.0}, {"timestamp": -31642200.0, "value": 66277.0}, {"timestamp": -106200.0, "value": 68507.0}, {"timestamp": 31429800.0, "value": 70742.0}, {"timestamp": 62965800.0, "value": 77519.0}, {"timestamp": 94588200.0, "value": 83953.0}, {"timestamp": 126124200.0, "value": 76657.0}, {"timestamp": 157660200.0, "value": 78797.0}, {"timestamp": 189196200.0, "value": 81120.0}, {"timestamp": 220818600.0, "value": 80706.0}, {"timestamp": 252354600.0, "value": 80417.0}, {"timestamp": 283890600.0, "value": 89386.0}, {"timestamp": 315426600.0, "value": 90492.0}, {"timestamp": 347049000.0, "value": 89830.0}, {"timestamp": 378585000.0, "value": 91882.0}, {"timestamp": 410121000.0, "value": 92285.0}, {"timestamp": 441657000.0, "value": 77773.0}, {"timestamp": 473279400.0, "value": 72628.0}, {"timestamp": 504815400.0, "value": 68240.0}, {"timestamp": 536351400.0, "value": 57456.0}, {"timestamp": 567887400.0, "value": 48042.0}, {"timestamp": 599509800.0, "value": 61078.0}, {"timestamp": 631045800.0, "value": 60134.0}, {"timestamp": 662581800.0, "value": 59839.0}, {"timestamp": 694117800.0, "value": 65630.0}, {"timestamp": 725740200.0, "value": 71137.0}, {"timestamp": 757276200.0, "value": 61536.0}, {"timestamp": 788812200.0, "value": 62136.0}, {"timestamp": 820348200.0, "value": 61871.0}, {"timestamp": 851970600.0, "value": 59975.0}, {"timestamp": 883506600.0, "value": 57705.0}, {"timestamp": 915042600.0, "value": 55893.0}, {"timestamp": 946578600.0, "value": 53379.0}, {"timestamp": 978201000.0, "value": 51350.0}, {"timestamp": 1009737000.0, "value": 48134.0}, {"timestamp": 1041273000.0, "value": 45400.0}, {"timestamp": 1072809000.0, "value": 48289.0}, {"timestamp": 1104431400.0, "value": 47993.0}, {"timestamp": 1135967400.0, "value": 47940.0}, {"timestamp": 1167503400.0, "value": 49703.0}, {"timestamp": 1199039400.0, "value": 51415.0}, {"timestamp": 1230661800.0, "value": 49094.0}, {"timestamp": 1262197800.0, "value": 49505.0}, {"timestamp": 1293733800.0, "value": 49617.0}, {"timestamp": 1325269800.0, "value": 49372.0}, {"timestamp": 1356892200.0, "value": 48976.0}, {"timestamp": 1388428200.0, "value": 47871.0}, {"timestamp": 1419964200.0, "value": 47045.0}, {"timestamp": 1451500200.0, "value": 46338.0}, {"timestamp": 1483122600.0, "value": 44866.0}, {"timestamp": 1514658600.0, "value": 43549.0}], "forecast_to": 1767119400.0}